[
  {
    "id": 1,
    "title": "Mobbin",
    "description": "Featuring over 500,000 screens and 1,000 iOS, Android & Web apps — New content weekly.",
    "imageUrl": "./assets/images/mobbin.svg",
    "url": "https://mobbin.com/?via=toools",
    "tag": "",
    "category": "",
    "createAt": "",
    "updatedAt": "",
    "submittedBy": ""
  },
  {
    "id": 1,
    "title": "Mobbin",
    "description": "Featuring over 500,000 screens and 1,000 iOS, Android & Web apps — New content weekly.",
    "imageUrl": "",
    "url": "https://mobbin.com/?via=toools",
    "tag": "",
    "category": "",
    "createAt": "",
    "updatedAt": "",
    "submittedBy": ""
  }
]
